{
    "作者": "年少轻狂",
    "站名": "",
    "请求头": "User-Agent$MOBILE_UA",
    "编码": "UTF-8",
    "图片代理": "0",
    "主页url": "https://m.douyu.com",
    "首页": "120",
    "起始页": "1",
    "分类url": "https://m.douyu.com/api/room/list?page={catePg}&type={cateId};;mrcd0",
    "分类": "网游竞技&单机热游&手游休闲&娱乐天地&颜值&科技文化&语音互动&语音直播&正能量&赛车竞技&京斗云&一起看&美食&竖屏美女",
    "分类值": "LOL&TVgame&wzry&ecy&yz&wh&paidui&yyjy&znl&eracing&jdy&yqk&ms&sy",
    "二次截取": "\"list&&nowPage",
    "数组": "{\"&&\"},",
    "标题": "roomName\":\"&&\"",
    "图片": "avatar\":\"&&\"",
    "副标题": "nickname\":\"&&\"",
    "链接": "https://m.douyu.com/+rid\":&&,",
    "解析": "",
    "直接播放": "1",
    "播放请求头": "",
    "嗅探词": "",
    "过滤词": "",
    "跳转播放链接": "",
    "跳转解析": ""
}