{
  "作者": "年少轻狂",
  "站名": "",
  "请求头": "User-Agent$MOBILE_UA",
  "编码": "UTF-8",
  "图片代理": "0",
  "主页url": "https://www.iermeiav.com",
  "首页": "120",
  "起始页": "1",
  "分类url": "https://www.iermeiav.com/vodshow/{cateId}-{area}-{by}-{class}-{lang}-{letter}---{catePg}---{year}.html;;mrcd0",
  "分类": "电影&剧集&综艺&动漫&短剧&直播",
  "分类值": "1&2&3&4&26&93",
  "二次截取": "mod-main\">&&</section>",
  "数组": "video-item\"&&</li>",
  "标题": "title=\"&&\"",
  "图片": "data-echo=\"&&\"",
  "副标题": "video-duration\">&&<",
  "链接": "href=\"&&\"",
  "影片年代": "年代：&&</li>",
  "影片地区": "地区：&&</li>",
  "影片类型": "类型：&&</p>",
  "状态": "状态：&&</li>",
  "导演": "导演：&&</li>",
  "主演": "主演：&&</li>",
  "简介": "👶+详情介绍：&&<br>",
  "线路二次截取": "id=\"playPathlist&&</div",
  "线路数组": "<li&&/li>",
  "线路标题": "👶+>&&<",
  "播放二次截取": "",
  "播放数组": "filmSelectWrap\">&&</div>",
  "播放列表": "<a&&/a>",
  "播放标题": ">&&<",
  "播放链接": "href=\"&&\"",
  "解析": "",
  "直接播放": "0",
  "播放请求头": "",
  "嗅探词": ".mp4#.m3u8",
  "过滤词": "",
  "跳转播放链接": "urlDecode(Base64(var player_*url\":\"&&\"))",
  "跳转解析": "",
  "搜索请求头": "User-Agent$MOBILE_UA",
  "搜索url": "https://www.iermeiav.com/vodsearch/{wd}----------{pg}---.html",
  "搜索模式": "1",
  "搜索后缀": "",
  "搜索二次截取": "",
  "搜索数组": "detail-wrap\">&&class=\"media-btn",
  "搜索标题": "title=\"&&\"",
  "搜索图片": "data-echo=\"&&\"",
  "搜索副标题": "",
  "搜索链接": "href=\"&&\"",
  "筛选": "1",
  "类型": "动作片$6#喜剧片$7#爱情片$8#科幻片$9#恐怖片$10#剧情片$11#犯罪片$136#战争片$12#电影解说$32||国产剧$13#港台剧$14#日韩剧$15#欧美剧$16#新马泰越$21||内地综艺$22#港台综艺$23#日韩综艺$24#欧美综艺$25#纪录片$20||动漫电影$105#国产动漫$28#日韩动漫$30#欧美动漫$31||空||精品轮播$99#有声电台$98#央视频道$94#卫视频道$95#全球电视频道$114#北京$192#天津$174#河北$175#安徽$184#山东$173#山西$176#辽宁$177#吉林$178#黑龙江$179#广西$191#江苏$181#浙江$182#上海$183#宁夏$169#福建$185#江西$186#湖北$188#湖南$189#广东$190#内蒙古$180#海南$172#重庆$171#四川$170#河南$187#青海$168#贵州$167#云南$166#陕西$165#甘肃$164#新疆$163#西藏$113#亚洲监控$193#非洲监控$194#欧洲监控$195",
  "剧情": "",
  "剧情值": "*",
  "地区": "",
  "地区值": "*",
  "年份": "",
  "年份值": "*",
  "语言": "",
  "语言值": "*",
  "字母": "A&B&C&D&E&F&G&H&I&J&K&L&M&N&O&P&Q&R&S&T&U&V&W&X&Y&Z&0-9",
  "字母值": "*",
  "排序": "时间&人气&评分",
  "排序值": "time&hits&score"
}