{
    "作者": "小可乐/240701/第一版",
    "站名": "PTT视频",
    "请求头": "User-Agent$MOBILE_UA",
    "编码": "UTF-8",
    "嗅探词": ".mp4#.m3u8",
    "主页url": "https://ptt.red/zh-hans",
    "首页": "120",
    "起始页": "1",
    "分类url": "/zh-hans/p/{cateId}{class}?page={catePg}&{area}&{year}&{by};;mrc",
    "分类": "电影&剧集&综艺&动漫&短剧&体育",
    "分类值": "1&3&2&4&66&53",
    "数组": "card\">&&/span>",
    "标题": "alt=\"&&\"",
    "图片": "src=\"&&\"",
    "副标题": "badge-success\">&&<",
    "链接": "href=\"&&\"[替换:/v>>空]+/1",
    "影片年代": "year\":&&,",
    "影片地区": "_area\":\"&&\"",
    "影片类型": "\"type\":\"&&\"",
    "状态": "note\":\"&&\"",
    "导演": "director\":\"&&\"",
    "主演": "actors\":\"&&\"",
    "简介": "请不要相信任何广告！！！祝您观影愉快！🐰兔爷🐇为您介绍剧情👉-+description\":\"&&\"",
    "线路数组": "px-2 nav-link&&/a>[排序:臥龍]",
    "线路标题": "title=\"&&\"",
    "多线数组": "px-2 nav-link&&/a>",
    "多线链接": "href=\"&&\"",
    "播放二次截取": "nav-tabs&&<table[替换:px-2 nav-link active>>mb-2 fullwidth\"><a>第1集<#nofollow\">>>/a></div>]",
    "播放数组": "mb-2 fullwidth\">&&</div>",
    "播放列表": "<a&&/a>",
    "播放标题": ">&&<",
    "播放链接": "href=\"&&\"",
    "跳转播放链接": "contentUrl\":\"&&\"",
    "搜索请求头": "User-Agent$MOBILE_UA",
    "搜索url": "/zh-hans/q/{wd}?page={pg}",
    "搜索模式": "1",
    "搜索数组": "card\">&&/span>",
    "搜索标题": "alt=\"&&\"",
    "搜索图片": "src=\"&&\"",
    "搜索副标题": "badge-success\">&&<",
    "搜索链接": "href=\"&&\"[替换:/v>>空]+/1",
    "筛选": {
        "1": [
            {
                "key": "class",
                "name": "剧情",
                "value": [
                    {
                        "n": "全部",
                        "v": ""
                    },
                    {
                        "n": "理论",
                        "v": "/c/33"
                    },
                    {
                        "n": "动作",
                        "v": "/c/5"
                    },
                    {
                        "n": "喜剧",
                        "v": "/c/6"
                    },
                    {
                        "n": "爱情",
                        "v": "/c/7"
                    },
                    {
                        "n": "科幻",
                        "v": "/c/8"
                    },
                    {
                        "n": "恐怖",
                        "v": "/c/9"
                    },
                    {
                        "n": "犯罪",
                        "v": "/c/10"
                    },
                    {
                        "n": "战争",
                        "v": "/c/11"
                    },
                    {
                        "n": "动漫",
                        "v": "/c/12"
                    },
                    {
                        "n": "剧情",
                        "v": "/c/13"
                    },
                    {
                        "n": "纪录",
                        "v": "/c/30"
                    },
                    {
                        "n": "悬疑",
                        "v": "/c/34"
                    },
                    {
                        "n": "动画",
                        "v": "/c/35"
                    },
                    {
                        "n": "其他",
                        "v": "/c/48"
                    },
                    {
                        "n": "解说",
                        "v": "/c/32"
                    }
                ]
            },
            {
                "key": "area",
                "name": "地区",
                "value": [
                    {
                        "n": "全部",
                        "v": ""
                    },
                    {
                        "n": "大陆",
                        "v": "area_id=2"
                    },
                    {
                        "n": "香港",
                        "v": "area_id=5"
                    },
                    {
                        "n": "台湾",
                        "v": "area_id=4"
                    },
                    {
                        "n": "韩国",
                        "v": "area_id=17"
                    },
                    {
                        "n": "日本",
                        "v": "area_id=18"
                    },
                    {
                        "n": "欧美",
                        "v": "area_id=6"
                    },
                    {
                        "n": "泰国",
                        "v": "area_id=10"
                    },
                    {
                        "n": "印度",
                        "v": "area_id=14"
                    },
                    {
                        "n": "其他",
                        "v": "area_id=3"
                    }
                ]
            },
            {
                "key": "year",
                "name": "时间",
                "value": [
                    {
                        "n": "全部",
                        "v": ""
                    },
                    {
                        "n": "2024",
                        "v": "year=2024"
                    },
                    {
                        "n": "2023",
                        "v": "year=2023"
                    },
                    {
                        "n": "2022",
                        "v": "year=2022"
                    },
                    {
                        "n": "2021",
                        "v": "year=2021"
                    },
                    {
                        "n": "2020",
                        "v": "year=2020"
                    },
                    {
                        "n": "2019",
                        "v": "year=2019"
                    },
                    {
                        "n": "2018",
                        "v": "year=2018"
                    },
                    {
                        "n": "2017",
                        "v": "year=2017"
                    },
                    {
                        "n": "2016",
                        "v": "year=2016"
                    },
                    {
                        "n": "2015",
                        "v": "year=2015"
                    },
                    {
                        "n": "2014",
                        "v": "year=2014"
                    }
                ]
            },
            {
                "key": "by",
                "name": "排序",
                "value": [
                    {
                        "n": "热播",
                        "v": ""
                    },
                    {
                        "n": "最新",
                        "v": "sort=last"
                    }
                ]
            }
        ],
        "3": [
            {
                "key": "class",
                "name": "剧情",
                "value": [
                    {
                        "n": "全部",
                        "v": ""
                    },
                    {
                        "n": "大陆",
                        "v": "/c/19"
                    },
                    {
                        "n": "香港",
                        "v": "/c/20"
                    },
                    {
                        "n": "台湾",
                        "v": "/c/81"
                    },
                    {
                        "n": "日本",
                        "v": "/c/83"
                    },
                    {
                        "n": "韩国",
                        "v": "/c/82"
                    },
                    {
                        "n": "欧美",
                        "v": "/c/22"
                    },
                    {
                        "n": "泰国",
                        "v": "/c/92"
                    },
                    {
                        "n": "其他",
                        "v": "/c/23"
                    }
                ]
            },
            {
                "key": "year",
                "name": "时间",
                "value": [
                    {
                        "n": "全部",
                        "v": ""
                    },
                    {
                        "n": "2024",
                        "v": "year=2024"
                    },
                    {
                        "n": "2023",
                        "v": "year=2023"
                    },
                    {
                        "n": "2022",
                        "v": "year=2022"
                    },
                    {
                        "n": "2021",
                        "v": "year=2021"
                    },
                    {
                        "n": "2020",
                        "v": "year=2020"
                    },
                    {
                        "n": "2019",
                        "v": "year=2019"
                    },
                    {
                        "n": "2018",
                        "v": "year=2018"
                    },
                    {
                        "n": "2017",
                        "v": "year=2017"
                    },
                    {
                        "n": "2016",
                        "v": "year=2016"
                    },
                    {
                        "n": "2015",
                        "v": "year=2015"
                    },
                    {
                        "n": "2014",
                        "v": "year=2014"
                    }
                ]
            },
            {
                "key": "by",
                "name": "排序",
                "value": [
                    {
                        "n": "热播",
                        "v": ""
                    },
                    {
                        "n": "最新",
                        "v": "sort=last"
                    }
                ]
            }
        ],
        "2": [
            {
                "key": "class",
                "name": "剧情",
                "value": [
                    {
                        "n": "全部",
                        "v": ""
                    },
                    {
                        "n": "大陆",
                        "v": "/c/15"
                    },
                    {
                        "n": "台湾",
                        "v": "/c/89"
                    },
                    {
                        "n": "香港",
                        "v": "/c/88"
                    },
                    {
                        "n": "日本",
                        "v": "/c/90"
                    },
                    {
                        "n": "韩国",
                        "v": "/c/91"
                    },
                    {
                        "n": "欧美",
                        "v": "/c/18"
                    },
                    {
                        "n": "其他",
                        "v": "/c/16"
                    }
                ]
            },
            {
                "key": "year",
                "name": "时间",
                "value": [
                    {
                        "n": "全部",
                        "v": ""
                    },
                    {
                        "n": "2024",
                        "v": "year=2024"
                    },
                    {
                        "n": "2023",
                        "v": "year=2023"
                    },
                    {
                        "n": "2022",
                        "v": "year=2022"
                    },
                    {
                        "n": "2021",
                        "v": "year=2021"
                    },
                    {
                        "n": "2020",
                        "v": "year=2020"
                    },
                    {
                        "n": "2019",
                        "v": "year=2019"
                    },
                    {
                        "n": "2018",
                        "v": "year=2018"
                    },
                    {
                        "n": "2017",
                        "v": "year=2017"
                    },
                    {
                        "n": "2016",
                        "v": "year=2016"
                    },
                    {
                        "n": "2015",
                        "v": "year=2015"
                    },
                    {
                        "n": "2014",
                        "v": "year=2014"
                    }
                ]
            },
            {
                "key": "by",
                "name": "排序",
                "value": [
                    {
                        "n": "热播",
                        "v": ""
                    },
                    {
                        "n": "最新",
                        "v": "sort=last"
                    }
                ]
            }
        ],
        "4": [
            {
                "key": "class",
                "name": "剧情",
                "value": [
                    {
                        "n": "全部",
                        "v": ""
                    },
                    {
                        "n": "大陆",
                        "v": "/c/26"
                    },
                    {
                        "n": "日本",
                        "v": "/c/86"
                    },
                    {
                        "n": "韩国",
                        "v": "/c/87"
                    },
                    {
                        "n": "欧美",
                        "v": "/c/27"
                    },
                    {
                        "n": "其他",
                        "v": "/c/28"
                    }
                ]
            },
            {
                "key": "year",
                "name": "时间",
                "value": [
                    {
                        "n": "全部",
                        "v": ""
                    },
                    {
                        "n": "2024",
                        "v": "year=2024"
                    },
                    {
                        "n": "2023",
                        "v": "year=2023"
                    },
                    {
                        "n": "2022",
                        "v": "year=2022"
                    },
                    {
                        "n": "2021",
                        "v": "year=2021"
                    },
                    {
                        "n": "2020",
                        "v": "year=2020"
                    },
                    {
                        "n": "2019",
                        "v": "year=2019"
                    },
                    {
                        "n": "2018",
                        "v": "year=2018"
                    },
                    {
                        "n": "2017",
                        "v": "year=2017"
                    },
                    {
                        "n": "2016",
                        "v": "year=2016"
                    },
                    {
                        "n": "2015",
                        "v": "year=2015"
                    },
                    {
                        "n": "2014",
                        "v": "year=2014"
                    }
                ]
            },
            {
                "key": "by",
                "name": "排序",
                "value": [
                    {
                        "n": "热播",
                        "v": ""
                    },
                    {
                        "n": "最新",
                        "v": "sort=last"
                    }
                ]
            }
        ],
        "66": [
            {
                "key": "class",
                "name": "剧情",
                "value": [
                    {
                        "n": "全部",
                        "v": ""
                    },
                    {
                        "n": "爽剧",
                        "v": "/c/67"
                    },
                    {
                        "n": "言情",
                        "v": "/c/68"
                    },
                    {
                        "n": "穿越",
                        "v": "/c/70"
                    },
                    {
                        "n": "悬疑",
                        "v": "/c/71"
                    },
                    {
                        "n": "古装",
                        "v": "/c/73"
                    },
                    {
                        "n": "都市",
                        "v": "/c/80"
                    },
                    {
                        "n": "甜宠",
                        "v": "/c/84"
                    },
                    {
                        "n": "虐恋",
                        "v": "/c/85"
                    },
                    {
                        "n": "其他",
                        "v": "/c/74"
                    }
                ]
            },
            {
                "key": "year",
                "name": "时间",
                "value": [
                    {
                        "n": "全部",
                        "v": ""
                    },
                    {
                        "n": "2024",
                        "v": "year=2024"
                    },
                    {
                        "n": "2023",
                        "v": "year=2023"
                    },
                    {
                        "n": "2022",
                        "v": "year=2022"
                    },
                    {
                        "n": "2021",
                        "v": "year=2021"
                    },
                    {
                        "n": "2020",
                        "v": "year=2020"
                    },
                    {
                        "n": "2019",
                        "v": "year=2019"
                    },
                    {
                        "n": "2018",
                        "v": "year=2018"
                    },
                    {
                        "n": "2017",
                        "v": "year=2017"
                    },
                    {
                        "n": "2016",
                        "v": "year=2016"
                    },
                    {
                        "n": "2015",
                        "v": "year=2015"
                    },
                    {
                        "n": "2014",
                        "v": "year=2014"
                    }
                ]
            },
            {
                "key": "by",
                "name": "排序",
                "value": [
                    {
                        "n": "热播",
                        "v": ""
                    },
                    {
                        "n": "最新",
                        "v": "sort=last"
                    }
                ]
            }
        ],
        "53": [
            {
                "key": "class",
                "name": "剧情",
                "value": [
                    {
                        "n": "全部",
                        "v": ""
                    },
                    {
                        "n": "足球",
                        "v": "/c/54"
                    },
                    {
                        "n": "篮球",
                        "v": "/c/55"
                    },
                    {
                        "n": "游戏",
                        "v": "/c/59"
                    },
                    {
                        "n": "台球",
                        "v": "/c/63"
                    },
                    {
                        "n": "网球",
                        "v": "/c/64"
                    },
                    {
                        "n": "其他",
                        "v": "/c/93"
                    }
                ]
            },
            {
                "key": "year",
                "name": "时间",
                "value": [
                    {
                        "n": "全部",
                        "v": ""
                    },
                    {
                        "n": "2024",
                        "v": "year=2024"
                    },
                    {
                        "n": "2023",
                        "v": "year=2023"
                    },
                    {
                        "n": "2022",
                        "v": "year=2022"
                    },
                    {
                        "n": "2021",
                        "v": "year=2021"
                    },
                    {
                        "n": "2020",
                        "v": "year=2020"
                    },
                    {
                        "n": "2019",
                        "v": "year=2019"
                    },
                    {
                        "n": "2018",
                        "v": "year=2018"
                    },
                    {
                        "n": "2017",
                        "v": "year=2017"
                    },
                    {
                        "n": "2016",
                        "v": "year=2016"
                    },
                    {
                        "n": "2015",
                        "v": "year=2015"
                    },
                    {
                        "n": "2014",
                        "v": "year=2014"
                    }
                ]
            },
            {
                "key": "by",
                "name": "排序",
                "value": [
                    {
                        "n": "热播",
                        "v": ""
                    },
                    {
                        "n": "最新",
                        "v": "sort=last"
                    }
                ]
            }
        ]
    }
}